edhoc/__init__.py
edhoc/definitions.py
edhoc/exceptions.py
edhoc/messages/__init__.py
edhoc/messages/base.py
edhoc/messages/error.py
edhoc/messages/message1.py
edhoc/messages/message2.py
edhoc/messages/message3.py
edhoc/roles/__init__.py
edhoc/roles/edhoc.py
edhoc/roles/initiator.py
edhoc/roles/responder.py
edhoc-0.2.dev3.dist-info/LICENSE
edhoc-0.2.dev3.dist-info/METADATA
edhoc-0.2.dev3.dist-info/WHEEL
edhoc-0.2.dev3.dist-info/top_level.txt
edhoc-0.2.dev3.dist-info/RECORD
