Metadata-Version: 2.1
Name: edhoc
Version: 0.2.dev3
Summary: Ephemeral Diffie-Hellman Over COSE (EDHOC)
Home-page: UNKNOWN
Author: Timothy Claeys
Author-email: timothy.claeys@gmail.com
License: BSD-3
Keywords: EDHOC,Internet of Things,CBOR,object security,COSE,OSCORE,cryptography
Platform: UNKNOWN
Classifier: Development Status :: 3 - Alpha
Classifier: Intended Audience :: Developers
Classifier: Topic :: Internet
Classifier: Topic :: Communications
Classifier: Topic :: Software Development
Classifier: Topic :: System :: Networking
Classifier: License :: OSI Approved :: BSD License
Classifier: Programming Language :: Python :: 3
Classifier: Programming Language :: Python :: 3.6
Classifier: Programming Language :: Python :: 3.7
Classifier: Programming Language :: Python :: 3.8
Requires-Python: >=3.6
Requires-Dist: cbor2 (>=5.2.0)
Requires-Dist: cryptography (>=3.2.1)
Requires-Dist: cose (==0.9.dev2)
Requires-Dist: aenum
Requires-Dist: aiocoap
